device_certificate_report/__init__.py
device_certificate_report/assets/logo.png
device_certificate_report/assets/logo.svg
device_certificate_report/components/__init__.py
device_certificate_report/components/data_collection.py
device_certificate_report/components/version.py
device_certificate_report/config/__init__.py
device_certificate_report/config/hardware_families.py
device_certificate_report/config/panos_versions.py
device_certificate_report/main.py
device_certificate_report/models/__init__.py
device_certificate_report/models/device.py
device_certificate_report/utilities/__init__.py
device_certificate_report/utilities/cleaner.py
device_certificate_report/utilities/filters.py
device_certificate_report/utilities/pdf_generation.py
device_certificate_report-0.1.2.dist-info/LICENSE
device_certificate_report-0.1.2.dist-info/METADATA
device_certificate_report-0.1.2.dist-info/WHEEL
device_certificate_report-0.1.2.dist-info/entry_points.txt
device_certificate_report-0.1.2.dist-info/RECORD
