Metadata-Version: 2.1
Name: device-certificate-report
Version: 0.1.2
Summary: A tool to generate device certificate reports from PAN-OS devices.
License: Apache 2.0
Keywords: paloaltonetworks,panos,firewall,certificate,report,automation
Author: Calvin Remsburg
Author-email: cremsburg.dev@gmail.com
Requires-Python: >=3.9,<4.0
Classifier: Development Status :: 4 - Beta
Classifier: Framework :: Flake8
Classifier: Framework :: MkDocs
Classifier: Framework :: Pydantic :: 2
Classifier: Intended Audience :: System Administrators
Classifier: License :: OSI Approved :: Apache Software License
Classifier: License :: Other/Proprietary License
Classifier: Natural Language :: English
Classifier: Operating System :: OS Independent
Classifier: Programming Language :: Python :: 3
Classifier: Programming Language :: Python :: 3.9
Classifier: Programming Language :: Python :: 3.10
Classifier: Programming Language :: Python :: 3.11
Classifier: Programming Language :: Python :: 3.12
Classifier: Topic :: Software Development :: Libraries :: Python Modules
Classifier: Topic :: System :: Networking :: Firewalls
Classifier: Topic :: System :: Systems Administration
Classifier: Topic :: Utilities
Requires-Dist: pan-os-python (>=1.12.1,<2.0.0)
Requires-Dist: pydantic (>=2.9.2,<3.0.0)
Requires-Dist: reportlab (>=4.2.2,<5.0.0)
Requires-Dist: setuptools (>=75.1.0,<76.0.0)
Requires-Dist: typer (>=0.12.5,<0.13.0)
Project-URL: Documentation, https://cdot65.github.io/device-certificate-report/
